aestetik/AESTETIK.py
aestetik/__init__.py
aestetik/dataloader.py
aestetik/utils/__init__.py
aestetik/utils/utils_clustering.py
aestetik/utils/utils_data.py
aestetik/utils/utils_grid.py
aestetik/utils/utils_morphology.py
aestetik/utils/utils_transcriptomics.py
aestetik/utils/utils_visualization.py
aestetik-0.1.0.dist-info/METADATA
aestetik-0.1.0.dist-info/WHEEL
aestetik-0.1.0.dist-info/top_level.txt
aestetik-0.1.0.dist-info/RECORD
