Metadata-Version: 2.4
Name: aestetik
Version: 0.1.0
Summary: AESTETIK: AutoEncoder for Spatial Transcriptomics Expression with Topology and Image Knowledge
Home-page: https://github.com/ratschlab/aestetik
Author: KalinNonchev
Author-email: boo@foo.com
License: MIT License
Requires-Python: >=3.9
Requires-Dist: torch==2.0.0
Requires-Dist: torchvision==0.15.1
Requires-Dist: lightning==2.3.0
Requires-Dist: numpy==1.23.5
Requires-Dist: pandas==1.5.3
Requires-Dist: scipy==1.11.4
Requires-Dist: anndata==0.8.0
Requires-Dist: scanpy==1.9.3
Requires-Dist: squidpy==1.2.2
Requires-Dist: matplotlib==3.8.2
Requires-Dist: scikit-learn==1.2.2
Requires-Dist: numba==0.56.4
Requires-Dist: llvmlite==0.39.1
Requires-Dist: dask-image==2022.9.0
Requires-Dist: plotnine
Dynamic: author
Dynamic: author-email
Dynamic: description
Dynamic: description-content-type
Dynamic: home-page
Dynamic: license
Dynamic: requires-dist
Dynamic: requires-python
Dynamic: summary
